Metadata-Version: 2.1
Name: odoo-addon-account_due_list_payment_mode
Version: 18.0.1.0.0.2
Requires-Python: >=3.10
Requires-Dist: odoo-addon-account_due_list==18.0.*
Requires-Dist: odoo-addon-account_payment_partner==18.0.*
Requires-Dist: odoo==18.0.*
Summary: Payment Due List Payment Mode
Home-page: https://github.com/OCA/account-payment
License: AGPL-3
Author: Obertix Free Solutions, Tecnativa, Odoo Community Association (OCA),
Author-email: support@odoo-community.org
Classifier: Programming Language :: Python
Classifier: Framework :: Odoo
Classifier: Framework :: Odoo :: 18.0
Classifier: License :: OSI Approved :: GNU Affero General Public License v3
